README.rst
parawrap.py
setup.py
parawrap.egg-info/PKG-INFO
parawrap.egg-info/SOURCES.txt
parawrap.egg-info/dependency_links.txt
parawrap.egg-info/top_level.txt
parawrap.egg-info/zip-safe