Metadata-Version: 1.1
Name: parawrap
Version: 1.0
Summary: Paragraph wrapping and filling.
Home-page: https://github.com/ecometrica/parawrap
Author: Ecometrica
Author-email: admin@ecometrica.com
License: Apache Software License, version 2.0
Platform: UNKNOWN
Classifier: Development Status :: 5 - Production/Stable
Classifier: Intended Audience :: Developers
Classifier: License :: OSI Approved :: Apache Software License
Classifier: Programming Language :: Python :: 2.6
Classifier: Programming Language :: Python :: 2.7
Classifier: Programming Language :: Python :: 3
Classifier: Topic :: Text Processing :: Filters
